{
  "id": "org.webosbrew.dtsenabler",
  "version": "1.0.0",
  "vendor": "webosbrew community (dts_restore by Pete Batard)",
  "type": "web",
  "main": "index.html",
  "title": "DTS Enabler",
  "icon": "icon.png",
  "largeIcon": "icon.png",
  "iconColor": "#101418",
  "bgColor": "#101418",
  "uiRevision": 2,
  "resolution": "1920x1080",
  "disableBackHistoryAPI": true,
  "handlesRelaunch": true,
  "requiredPermissions": [
    "activitymanager.read",
    "activitymanager.write"
  ],
  "_comment_permissions": "This web app does NOT itself hold root. All privileged work is delegated to the Homebrew Channel exec service (luna://org.webosbrew.hbchannel.service/exec), which the app calls from its own JS service. The app therefore only needs the standard permissions to talk to Luna. On a rooted TV, luna access is unrestricted; on retail firmware these luna calls would be rejected by ACG, which is expected: this app is meaningless without root.",
  "_comment_icon": "icon.png must be a real 80x80 PNG for on-TV display. A vector source (icon.svg) is provided; convert it with e.g. `rsvg-convert -w 80 -h 80 icon.svg > icon.png` or any tool before packaging. See README > Icon."
}
